{
  "indexes": [
    {
      "collectionGroup": "messages",
      "queryScope": "COLLECTION",
      "fields": [
        { "fieldPath": "roomId", "order": "ASCENDING" },
        { "fieldPath": "createdAt", "order": "ASCENDING" }
      ]
    },
    {
      "collectionGroup": "sessions",
      "queryScope": "COLLECTION",
      "fields": [
        { "fieldPath": "userId", "order": "ASCENDING" },
        { "fieldPath": "startTime", "order": "DESCENDING" }
      ]
    },
    {
      "collectionGroup": "sessions",
      "queryScope": "COLLECTION",
      "fields": [
        { "fieldPath": "userId", "order": "ASCENDING" },
        { "fieldPath": "startTime", "order": "ASCENDING" }
      ]
    },
    {
      "collectionGroup": "sessions",
      "queryScope": "COLLECTION",
      "fields": [
        { "fieldPath": "userId", "order": "ASCENDING" },
        { "fieldPath": "startTime", "order": "ASCENDING" },
        { "fieldPath": "__name__", "order": "ASCENDING" }
      ]
    },
    {
      "collectionGroup": "sessions",
      "queryScope": "COLLECTION",
      "fields": [
        { "fieldPath": "userId", "order": "ASCENDING" },
        { "fieldPath": "startTime", "order": "DESCENDING" },
        { "fieldPath": "__name__", "order": "DESCENDING" }
      ]
    },
    {
      "collectionGroup": "sessionReactions",
      "queryScope": "COLLECTION",
      "fields": [
        { "fieldPath": "sessionId", "order": "ASCENDING" },
        { "fieldPath": "createdAt", "order": "ASCENDING" }
      ]
    },
    {
      "collectionGroup": "sessionReactions",
      "queryScope": "COLLECTION",
      "fields": [
        { "fieldPath": "fromUserId", "order": "ASCENDING" },
        { "fieldPath": "createdAt", "order": "ASCENDING" }
      ]
    }
  ],
  "fieldOverrides": [
    {
      "collectionGroup": "members",
      "fieldPath": "userId",
      "indexes": [
        { "order": "ASCENDING", "queryScope": "COLLECTION_GROUP" },
        { "order": "ASCENDING", "queryScope": "COLLECTION" },
        { "order": "DESCENDING", "queryScope": "COLLECTION" }
      ]
    }
  ]
}

